signalads.py
signalads-0.0.10.dist-info/METADATA
signalads-0.0.10.dist-info/WHEEL
signalads-0.0.10.dist-info/top_level.txt
signalads-0.0.10.dist-info/RECORD
