Metadata-Version: 2.1
Name: signalads
Version: 0.0.10
Summary: Signal Ads Python library
Home-page: https://github.com/signalads-co/signalads-python
Author: Iman Naseri
Author-email: inaseri.20@gmail.com
Keywords: signalads,sms,signal
Classifier: Programming Language :: Python :: 3
Classifier: License :: OSI Approved :: MIT License
Classifier: Operating System :: OS Independent
Requires-Dist: requests (>=0.10.8)
